frigg_coverage/__init__.py
frigg_coverage/parsers/__init__.py
frigg_coverage/parsers/clover.py
frigg_coverage/parsers/cobertura.py
frigg_coverage/parsers/go_cover.py
frigg_coverage/parsers/go_coverprofile.py
frigg_coverage-1.2.0.dist-info/DESCRIPTION.rst
frigg_coverage-1.2.0.dist-info/METADATA
frigg_coverage-1.2.0.dist-info/metadata.json
frigg_coverage-1.2.0.dist-info/RECORD
frigg_coverage-1.2.0.dist-info/top_level.txt
frigg_coverage-1.2.0.dist-info/WHEEL
