Metadata-Version: 2.0
Name: frigg-coverage
Version: 1.2.0
Summary: Coverage report reading util
Home-page: https://github.com/frigg/frigg-coverage
Author: The frigg team
Author-email: hi@frigg.io
License: MIT
Platform: UNKNOWN
Classifier: Programming Language :: Python
Classifier: Programming Language :: Python :: 3
